urbalurba_logging/__init__.py
urbalurba_logging/lib_test.py
urbalurba_logging/log_levels.py
urbalurba_logging/urblogger.py
urbalurba_logging-1.0.6.dist-info/METADATA
urbalurba_logging-1.0.6.dist-info/WHEEL
urbalurba_logging-1.0.6.dist-info/entry_points.txt
urbalurba_logging-1.0.6.dist-info/top_level.txt
urbalurba_logging-1.0.6.dist-info/RECORD
