Metadata-Version: 2.4
Name: urbalurba-logging
Version: 1.0.6
Summary: Professional structured logging library following 'Loggeloven av 2025' requirements
Author-email: Terje Christensen <integration-platform@redcross.no>
Project-URL: Homepage, https://github.com/terchris/urbalurba-logging
Project-URL: Bug Tracker, https://github.com/terchris/urbalurba-logging/issues
Project-URL: Documentation, https://github.com/terchris/urbalurba-logging/blob/main/python/README-python.md
Project-URL: Source Code, https://github.com/terchris/urbalurba-logging/tree/main/python
Keywords: logging,structured-logging,json,opentelemetry,azure-monitor,observability
Classifier: Development Status :: 5 - Production/Stable
Classifier: Intended Audience :: Developers
Classifier: Topic :: Software Development :: Libraries :: Python Modules
Classifier: Topic :: System :: Logging
Classifier: License :: OSI Approved :: MIT License
Classifier: Programming Language :: Python :: 3
Classifier: Programming Language :: Python :: 3.8
Classifier: Programming Language :: Python :: 3.9
Classifier: Programming Language :: Python :: 3.10
Classifier: Programming Language :: Python :: 3.11
Classifier: Programming Language :: Python :: 3.12
Classifier: Operating System :: OS Independent
Requires-Python: >=3.8
Requires-Dist: structlog>=23.1.0
Requires-Dist: opentelemetry-api>=1.21.0
Requires-Dist: opentelemetry-sdk>=1.21.0
Requires-Dist: opentelemetry-exporter-otlp>=1.21.0
Requires-Dist: opentelemetry-exporter-otlp-proto-http>=1.21.0
Requires-Dist: opentelemetry-semantic-conventions>=0.44b0
Requires-Dist: requests>=2.31.0
Provides-Extra: dev
Requires-Dist: pytest>=7.0.0; extra == "dev"
Requires-Dist: pytest-asyncio>=0.21.0; extra == "dev"
Requires-Dist: black>=23.0.0; extra == "dev"
Requires-Dist: flake8>=6.0.0; extra == "dev"
Requires-Dist: mypy>=1.0.0; extra == "dev"
Requires-Dist: python-dotenv>=1.0.0; extra == "dev"
Requires-Dist: aiohttp>=3.8.0; extra == "dev"
Provides-Extra: examples
Requires-Dist: python-dotenv>=1.0.0; extra == "examples"
Requires-Dist: aiohttp>=3.8.0; extra == "examples"
Requires-Dist: requests>=2.31.0; extra == "examples"
